{"projectData":{"createDateStr":"2017-12-26","user":{"name":"段超","id":6},"id":67,"version":"0.0.0.5","introduction":"","name":"极验验证","moduleList":[{"id":96,"introduction":"","name":"某模块（点击编辑后双击修改）","pageList":[{"id":245,"introduction":"","name":"某页面","actionList":[{"id":1584,"name":"初始化得到challenge","description":"","requestType":"1","requestUrl":"krspace-gateway-wap/web/login/startCaptcha","responseTemplate":"","requestParameterList":[{"id":20773,"identifier":"phone","name":"","remark":"手机号","parameterList":[],"validator":"","dataType":"string"}],"responseParameterList":[{"id":20754,"identifier":"message","name":"","remark":"@mock=ok","parameterList":[],"validator":"","dataType":"string"},{"id":20750,"identifier":"data","name":"","remark":"","parameterList":[{"id":20751,"identifier":"challenge","name":"","remark":"@mock=e8882f674d74cdc238b93bb93a3289b8","parameterList":[],"validator":"","dataType":"string"},{"id":20753,"identifier":"success","name":"","remark":"@mock=1","parameterList":[],"validator":"","dataType":"number"},{"id":20766,"identifier":"new_captcha","name":"连接不上服务，很少出现","remark":"网站主服务器连接不上极验云服务器时的一种应急处理模式","parameterList":[],"validator":"","dataType":"boolean"},{"id":20752,"identifier":"gt","name":"","remark":"@mock=41dee9d0d758148b2d15e0050bd37b63","parameterList":[],"validator":"","dataType":"string"}],"validator":"","dataType":"object"},{"id":20749,"identifier":"code","name":"","remark":"@mock=1","parameterList":[],"validator":"","dataType":"number"}]},{"id":1585,"name":"发送短信码","description":"","requestType":"2","requestUrl":"krspace-gateway-wap/web/login/get-verify-code","responseTemplate":"","requestParameterList":[{"id":20756,"identifier":"geetest_seccode","name":"","remark":"极验验证二次验证表单数据 seccode","parameterList":[],"validator":"","dataType":"string"},{"id":20757,"identifier":"geetest_validate","name":"","remark":"极验验证二次验证表单数据 validate","parameterList":[],"validator":"","dataType":"string"},{"id":20755,"identifier":"geetest_challenge","name":"","remark":"极验验证二次验证表单数据 chllenge","parameterList":[],"validator":"","dataType":"string"},{"id":20758,"identifier":"phone","name":"","remark":"","parameterList":[],"validator":"","dataType":"string"}],"responseParameterList":[{"id":20760,"identifier":"data","name":"","remark":"","parameterList":[{"id":20763,"identifier":"value","name":"","remark":"1  ||0","parameterList":[],"validator":"","dataType":"number"},{"id":20762,"identifier":"status","name":"","remark":"success  ||fail","parameterList":[],"validator":"","dataType":"string"},{"id":20761,"identifier":"message","name":"","remark":"发送成功 !  ||发送失败","parameterList":[],"validator":"","dataType":"string"},{"id":20764,"identifier":"version","name":"","remark":"@mock=4.0","parameterList":[],"validator":"","dataType":"string"}],"validator":"","dataType":"object"},{"id":20765,"identifier":"message","name":"","remark":"@mock=ok","parameterList":[],"validator":"","dataType":"string"},{"id":20759,"identifier":"code","name":"","remark":"@mock=1","parameterList":[],"validator":"","dataType":"number"}]}]}]}]},"relatedIds":"","checkList":[{"id":4641,"version":"0.0.0.6","userName":"段超","createDateStr":"2018-01-02 09:42:38","description":"quick save"},{"id":4637,"version":"0.0.0.5","userName":"段超","createDateStr":"2017-12-26 17:52:51","description":"quick save"},{"id":4636,"version":"0.0.0.4","userName":"段超","createDateStr":"2017-12-26 17:37:50","description":"quick save"},{"id":4635,"version":"0.0.0.3","userName":"段超","createDateStr":"2017-12-26 17:36:47","description":"quick save"},{"id":4634,"version":"0.0.0.2","userName":"段超","createDateStr":"2017-12-26 17:26:09","description":"quick save"}]}